[
    {
      "ChapterName": "Energy Flow in an Ecosystem",
      "Videos": [
        {
          "VN": "Part 1",
          "VL": "https://youtu.be/e6pDVFo7y7s"
        },
        {
          "VN": "Part 2",
          "VL": "https://youtu.be/dkDWo6GT4yM"
        },
        {
          "VN": "Part 3",
          "VL": "https://youtu.be/NvNG6S3pc98"
        },
        {
          "VN": "Part 4",
          "VL": "https://youtu.be/T3c7paUYSxg"
        }
      ],
      "StudyMaterial":[
        {
          "MN": "",
          "ML": ""
        }
      ]
    }
]
