  [
    {
      "ChapterName": "मराठी व्याकरण",
      "Videos": [
        {
          "VN": "जाहिरात लेखन #1",
          "VL": "https://youtu.be/-ak7PYEY6_M"
        },
        {
          "VN": "बातमी लेखन #2",
          "VL": "https://youtu.be/4FtO_eQ_Ix0"
        },
        {
          "VN": "कथालेखन #3",
          "VL": "https://youtu.be/chjdDN81Q8U"
        }
      ],
      "StudyMaterial":[
        {
          "MN": "",
          "ML": ""
        }
      ]
    },
    {
      "ChapterName": "कृतीपत्रिका आराखडा",
      "Videos": [
        {
          "VN": "भाग १",
          "VL": "https://youtu.be/htSv2ezlsck"
        }
      ],
      "StudyMaterial":[
        {
          "MN": "",
          "ML": ""
        }
      ]
    },
    {
      "ChapterName": "संतवाणी",
      "Videos": [
        {
          "VN": "(अ) जैसा वृक्ष नेणे- संत नामदेव",
          "VL": "https://youtu.be/65qzrBqAqtA"
        }
      ],
      "StudyMaterial":[
        {
          "MN": "",
          "ML": ""
        }
      ]
    }
]
